pyceau/__init__.py
pyceau/pyceau.py
pyceau-0.0.7.data/scripts/pyceau
pyceau-0.0.7.dist-info/AUTHORS
pyceau-0.0.7.dist-info/METADATA
pyceau-0.0.7.dist-info/WHEEL
pyceau-0.0.7.dist-info/pbr.json
pyceau-0.0.7.dist-info/top_level.txt
pyceau-0.0.7.dist-info/RECORD
