Metadata-Version: 2.1
Name: pyceau
Version: 0.0.7
Summary: 2D cellular automata without colors using Moore neighbourhood
Home-page: UNKNOWN
Author: Felix
Author-email: pypi@flx.ai
License: UNKNOWN
Project-URL: Source Code, https://github.com/flxai/pyceau
Project-URL: Bug Tracker, https://github.com/flxai/pyceau/issues
Project-URL: Documentation, https://pyceau.readthedocs.io
Platform: UNKNOWN
Requires-Dist: pbr (==5.4.4)
Requires-Dist: Pillow (==8.3.2)
